<?xml version='1.0'?>
<?xml-stylesheet type='text/xsl' href='note.xsl'?>
<note title="[LibertyPrimeTerminalNote2a]">
<p>Im Folgenden die Ergebnisse der aktuellsten Roboterdiagnose:</p>
<p></p>
<p>Mobilität: 0 %</p>
<p>Navigationsübersetzung: 0 %</p>
<p>Interne Prozessoren: 46 %</p>
<p>Waffensysteme: 45 %</p>
<p>Energiemanagement: 37 %</p>
<p>Stimmmodul: 100 %</p>
<p></p>
<p>Der Gelehrte Rothchild ist zuversichtlich, dass wir durch Umleitung der Energie von den Waffen- und Mobilitätssubsystemen das Energiemanagement auf mindestens 67 % bringen können - genug, um eine vollständige Aktivierungssequenz durchführen zu können.</p>
</note>
