<?xml version='1.0'?>
<?xml-stylesheet type='text/xsl' href='note.xsl'?>
<note title="Aufseher-Brief (Braun)">
<p>Ein Brief an den Aufseher - von Dr. Stanislaus Braun:</p>
<p></p>
<p>Wenn Sie dies lesen, wurden die Notfallmaßnahmen zur Vault-Internierung eingeleitet und Sie mit Ihrer Kontrollgruppe in Ihrer Vault eingeschlossen. Herzlichen Glückwunsch! Sie sind jetzt ein wichtiger Bestandteil des ehrgeizigsten Programms, das Vault-Tec je unternommen hat.</p>
<p></p>
<p>Falls Sie Ihre versiegelten Befehle noch nicht gelesen haben, dann holen Sie dies jetzt nach. In diesen Befehlen werden die Ihrer Kontrollgruppe zugeteilten Experimentalprotokolle beschrieben. Bitte denken Sie daran, dass jedwede Abweichung von diesen Protokollen den Erfolg des Programms gefährdet und von der Vault-Tec Corporation gemäß den Statuten Ihres Einstellungsvertrags als Kündigungsgrund erachtet werden kann.</p>
<p></p>
<p>Ihrer Vault wurde evtl. ein G.E.E.K.-Modul zugewiesen. Einzelheiten siehe Anlage A.</p>
<p></p>
<p>Doktor Stanislaus Braun</p>
<p>Direktor, Programm zur Erhaltung der Gesellschaft</p>
<p>Vault-Tec Corporation</p>
</note>
