<?xml version='1.0'?>
<?xml-stylesheet type='text/xsl' href='note.xsl'?>
<note title="Ödland-Überlebenshandbuch 4">
<p>Verfasserin: Moira Brown</p>
<p>Wissenschaftler: &amp;PCName;</p>
<p></p>
<p>Dieses bescheidene Reisehandbuch ist für erfahrene Ödlandüberlebende nur von geringem Nutzen, könnte aber als recht gutes Handbuch für Anfänger betrachtet werden.</p>
<p></p>
<p>Das unübersehbare Engagement des Verfassers inspiriert den Leser zu neuen Sichtweisen in Bezug auf den Aufbau lebensfähiger Siedlungen und die Nutzung alter Technologien. Diese edlen Ideale werden aber oft durch gefährlich irreführende Überlebenstipps und weitschweifige Passagen über die Bewohner des Ödlands verwässert.</p>
<p></p>
<p>Sein bissiger Ton kann zwar amüsant sein, aber wegen der geringen Qualität des Inhalts muss man sich fragen, ob die Verfasser dem Leser wirklich helfen oder ihn in sein Verderben führen wollen.</p>
</note>
