<?xml version="1.0"?>
<?xml-stylesheet type="text/xsl" href="buch.xsl"?>
<buch name="Nachricht von Nelos" preis="1" gewicht="0.10">
<p>
<br />Maurrie,<br /><br />wahrlich, ich war von Euch entzückt von dem Moment an, als ich Euch sah. Ich bitte Euch um Verzeihung für meine früheren Vergehen. Ich kann mir zwar nicht vorstellen, was eine Frau von Eurer Schönheit und Bildung in einem Schurken wie mir sehen könnte, aber ich danke den Göttern, dass Ihr nach mir geschickt habt. Ich werde so schnell kommen, wie es mir möglich ist. Bis dahin.<br /><br />Der Eurige,<br /><br />Nelos<br />
</p>
</buch>
