<?xml version="1.0"?>
<?xml-stylesheet type="text/xsl" href="buch.xsl"?>
<buch name="Brief an Yngling" preis="100" gewicht="0.20">
<p>
<br />Ser Yngling,<br /><br />ich muss gestehen, dass ich ob Eurer Anfrage nach Geldern, um den Tempel des Hauses Hlaalu in Vivec instand zu setzen, überrascht war. Vor unserem Treffen letzte Woche wusste ich lediglich, dass Ihr ein Fremdländer seid und kein Mitglied unseres Tempels. Ich möchte Euch noch einmal darum bitten, einem alten Mann zu vergeben, dass er falschen Gerüchten Glauben geschenkt hat. Nun, da ich Euch persönlich kennen gelernt habe, bin ich mir sicher, dass Eure Motive nur die edelsten sind und dass Ihr den Tempel wieder zu seiner vorherigen Pracht aufbauen könnt.<br /><br />Das Haus Hlaalu hat seinen Tempel in Vivec schon viele Jahre lang nicht mehr gepflegt und er befindet sich in einem Zustand des Verfalls. Da ich mir der äußerst schwierigen Aufgabe der Restauration bewusst bin, wäre es mir ein besonderes Anliegen, Euch 50.000 Draken für Eure Bemühungen zur Verfügung zu stellen.<br /><br />Erzkanoniker Saryoni<br />
</p>
</buch>
